pratt_calc/__init__.py
pratt_calc/evaluator.py
pratt_calc/repl.py
pratt_calc/tokenizer.py
pratt_calc-2.0.6.dist-info/licenses/LICENSE
pratt_calc-2.0.6.dist-info/WHEEL
pratt_calc-2.0.6.dist-info/entry_points.txt
pratt_calc-2.0.6.dist-info/METADATA
pratt_calc-2.0.6.dist-info/RECORD
