Metadata-Version: 2.4
Name: pratt-calc
Version: 2.0.6
Summary: Arithmetic calculator which uses a Pratt parser
Author: Brandon C. Irizarry
Author-email: Brandon C. Irizarry <brandon.irizarry@gmail.com>
License-Expression: GPL-3.0-or-later
License-File: LICENSE
Classifier: Programming Language :: Python :: 3
Classifier: Operating System :: OS Independent
Requires-Dist: more-itertools>=10.8.0
Requires-Dist: typer>=0.20.0
Requires-Python: >=3.13
Project-URL: Homepage, https://github.com/BrandonIrizarry/pratt_calc
